{
  "id": "sample",
  "name": "sample",
  "public": false,
  "manifestVersion": 1,
  "version": "1.0.0",
  "description": "Sample Azure DevOps extension with hot reload",
  "publisher": "litra",
  "demands": [ "api-version/3.0" ],
  "categories": [ "Azure Repos" ],
  "targets": [
    {
      "id": "Microsoft.VisualStudio.Services"
    }
  ],
  "content": {
    "details": {
      "path": "README.md"
    }
  },
  "icons": {
    "default": "img/world.png"
  },
  "files": [
    {
      "path": "dist",
      "addressable": true
    },
    {
      "path": "img",
      "addressable": true
    }
  ],
  "contributions": [
    {
      "id": "sample-hub-group",
      "type": "ms.vss-web.hub-group",
      "description": "Sample hub group",
      "targets": [ "ms.vss-web.project-hub-groups-collection" ],
      "properties": {
        "name": "Sample",
        "icon": {
          "dark": "img/world.png",
          "light": "img/world.png"
        }
      }
    },
    {
      "id": "default-hub",
      "type": "ms.vss-web.hub",
      "targets": [ ".sample-hub-group" ],
      "properties": {
        "uri": "dist/main.html"
      }
    }
  ]
}
